<xml version="1.0" encoding="UTF-8" id="showphotos_xml" style="display:none"><rows height="30" valign="middle"><row id="8305c17ab4aab6d767facbae66a18b97">
                            <cell style ="vertical-align:middle;text-align: center;"></cell>
                            <cell style ="vertical-align:middle;text-align: left;">
                            &lt;img src="http://www.parentfinder.com/m/photos/get_image/file/8305c17ab4aab6d767facbae66a18b97.jpg" height="50" width="50"/&gt;</cell>
                            <cell style ="vertical-align:middle;white-space:normal;">Chris & Julie</cell>
                        </row></rows></xml>