<xml version="1.0" encoding="UTF-8" id="showphotos_xml" style="display:none"><rows height="30" valign="middle"><row id="d56ba13617f5ca222442227cd0388f57">
                            <cell style ="vertical-align:middle;text-align: center;"></cell>
                            <cell style ="vertical-align:middle;text-align: left;"><![CDATA[
                            <img src="http://ctstagepf.parentfinder.com/m/photos/get_image/file/d56ba13617f5ca222442227cd0388f57.jpg" height="50" width="50"/>]]></cell>
                            <cell style ="vertical-align:middle;white-space:normal;"><![CDATA[01518_monaco_1920x1080.jpg]]></cell>
                        </row><row id="6114fdbb5896ba8d4bd4c8906a05ff71">
                            <cell style ="vertical-align:middle;text-align: center;"></cell>
                            <cell style ="vertical-align:middle;text-align: left;"><![CDATA[
                            <img src="http://ctstagepf.parentfinder.com/m/photos/get_image/file/6114fdbb5896ba8d4bd4c8906a05ff71.jpg" height="50" width="50"/>]]></cell>
                            <cell style ="vertical-align:middle;white-space:normal;"><![CDATA[1747536.jpg]]></cell>
                        </row><row id="376ff00f9c2c4a5952592017b6276340">
                            <cell style ="vertical-align:middle;text-align: center;"></cell>
                            <cell style ="vertical-align:middle;text-align: left;"><![CDATA[
                            <img src="http://ctstagepf.parentfinder.com/m/photos/get_image/file/376ff00f9c2c4a5952592017b6276340.jpg" height="50" width="50"/>]]></cell>
                            <cell style ="vertical-align:middle;white-space:normal;"><![CDATA[02934_weatheredcliffs_672x420.jpg]]></cell>
                        </row><row id="1485c4d6b1a9297000a8ca386375a097">
                            <cell style ="vertical-align:middle;text-align: center;"></cell>
                            <cell style ="vertical-align:middle;text-align: left;"><![CDATA[
                            <img src="http://ctstagepf.parentfinder.com/m/photos/get_image/file/1485c4d6b1a9297000a8ca386375a097.jpg" height="50" width="50"/>]]></cell>
                            <cell style ="vertical-align:middle;white-space:normal;"><![CDATA[Blue-Robin-wallpaper-1024x640.jpg]]></cell>
                        </row><row id="736df0ac87df877d7b1e8d924b22df53">
                            <cell style ="vertical-align:middle;text-align: center;"></cell>
                            <cell style ="vertical-align:middle;text-align: left;"><![CDATA[
                            <img src="http://ctstagepf.parentfinder.com/m/photos/get_image/file/736df0ac87df877d7b1e8d924b22df53.jpg" height="50" width="50"/>]]></cell>
                            <cell style ="vertical-align:middle;white-space:normal;"><![CDATA[cast_off_desktops.jpg]]></cell>
                        </row></rows></xml>