<xml version="1.0" encoding="UTF-8" id="show_photos_xml" style="display:none"><rows height="30" valign="middle"><row id="8b3add6313201d18b3bd4b5fb22919e2">
                            <cell style ="vertical-align:middle;text-align: center;"></cell>
                            <cell style ="vertical-align:middle;text-align: left;">
                            &lt;img src="http://www.parentfinder.com/m/photos/get_image/file/8b3add6313201d18b3bd4b5fb22919e2.jpg" height="50" width="50"/&gt;</cell>
                        </row><row id="f1d3b9e6c0f4e52b257d9985c010f473">
                            <cell style ="vertical-align:middle;text-align: center;"></cell>
                            <cell style ="vertical-align:middle;text-align: left;">
                            &lt;img src="http://www.parentfinder.com/m/photos/get_image/file/f1d3b9e6c0f4e52b257d9985c010f473.jpg" height="50" width="50"/&gt;</cell>
                        </row><row id="fbb5cdad126a346337bbd46d71f4b71d">
                            <cell style ="vertical-align:middle;text-align: center;"></cell>
                            <cell style ="vertical-align:middle;text-align: left;">
                            &lt;img src="http://www.parentfinder.com/m/photos/get_image/file/fbb5cdad126a346337bbd46d71f4b71d.jpg" height="50" width="50"/&gt;</cell>
                        </row><row id="fa772674885739be89305ee338a7dfaa">
                            <cell style ="vertical-align:middle;text-align: center;"></cell>
                            <cell style ="vertical-align:middle;text-align: left;">
                            &lt;img src="http://www.parentfinder.com/m/photos/get_image/file/fa772674885739be89305ee338a7dfaa.jpg" height="50" width="50"/&gt;</cell>
                        </row><row id="aaec5fd69e09d11993295a02172ebea9">
                            <cell style ="vertical-align:middle;text-align: center;"></cell>
                            <cell style ="vertical-align:middle;text-align: left;">
                            &lt;img src="http://www.parentfinder.com/m/photos/get_image/file/aaec5fd69e09d11993295a02172ebea9.jpg" height="50" width="50"/&gt;</cell>
                        </row><row id="58b37eebc6d64ebec2f637e41c6d0c1b">
                            <cell style ="vertical-align:middle;text-align: center;"></cell>
                            <cell style ="vertical-align:middle;text-align: left;">
                            &lt;img src="http://www.parentfinder.com/m/photos/get_image/file/58b37eebc6d64ebec2f637e41c6d0c1b.jpg" height="50" width="50"/&gt;</cell>
                        </row><row id="6fc3038d07b8ab178c7aea392c9365f5">
                            <cell style ="vertical-align:middle;text-align: center;"></cell>
                            <cell style ="vertical-align:middle;text-align: left;">
                            &lt;img src="http://www.parentfinder.com/m/photos/get_image/file/6fc3038d07b8ab178c7aea392c9365f5.jpg" height="50" width="50"/&gt;</cell>
                        </row><row id="834563f872b2c1664ea63cad1c77f962">
                            <cell style ="vertical-align:middle;text-align: center;"></cell>
                            <cell style ="vertical-align:middle;text-align: left;">
                            &lt;img src="http://www.parentfinder.com/m/photos/get_image/file/834563f872b2c1664ea63cad1c77f962.jpg" height="50" width="50"/&gt;</cell>
                        </row><row id="61a85b3733ba6ae32276f158008c99eb">
                            <cell style ="vertical-align:middle;text-align: center;"></cell>
                            <cell style ="vertical-align:middle;text-align: left;">
                            &lt;img src="http://www.parentfinder.com/m/photos/get_image/file/61a85b3733ba6ae32276f158008c99eb.jpg" height="50" width="50"/&gt;</cell>
                        </row><row id="abe11c3293c23a4b76fe4ffedcfb2afe">
                            <cell style ="vertical-align:middle;text-align: center;"></cell>
                            <cell style ="vertical-align:middle;text-align: left;">
                            &lt;img src="http://www.parentfinder.com/m/photos/get_image/file/abe11c3293c23a4b76fe4ffedcfb2afe.jpg" height="50" width="50"/&gt;</cell>
                        </row><row id="d347236c3c84448ecbf9ae3c10e2a0ab">
                            <cell style ="vertical-align:middle;text-align: center;"></cell>
                            <cell style ="vertical-align:middle;text-align: left;">
                            &lt;img src="http://www.parentfinder.com/m/photos/get_image/file/d347236c3c84448ecbf9ae3c10e2a0ab.jpg" height="50" width="50"/&gt;</cell>
                        </row><row id="41221c24b8bfea572fd8c7b8592da174">
                            <cell style ="vertical-align:middle;text-align: center;"></cell>
                            <cell style ="vertical-align:middle;text-align: left;">
                            &lt;img src="http://www.parentfinder.com/m/photos/get_image/file/41221c24b8bfea572fd8c7b8592da174.jpg" height="50" width="50"/&gt;</cell>
                        </row><row id="a846bf3fb881a95f1eceeb2ced54df88">
                            <cell style ="vertical-align:middle;text-align: center;"></cell>
                            <cell style ="vertical-align:middle;text-align: left;">
                            &lt;img src="http://www.parentfinder.com/m/photos/get_image/file/a846bf3fb881a95f1eceeb2ced54df88.jpg" height="50" width="50"/&gt;</cell>
                        </row><row id="d2ac96749d9c4deb08709851853b45a1">
                            <cell style ="vertical-align:middle;text-align: center;"></cell>
                            <cell style ="vertical-align:middle;text-align: left;">
                            &lt;img src="http://www.parentfinder.com/m/photos/get_image/file/d2ac96749d9c4deb08709851853b45a1.jpg" height="50" width="50"/&gt;</cell>
                        </row><row id="235bf39221257a124f51c9fbb8c14a8f">
                            <cell style ="vertical-align:middle;text-align: center;"></cell>
                            <cell style ="vertical-align:middle;text-align: left;">
                            &lt;img src="http://www.parentfinder.com/m/photos/get_image/file/235bf39221257a124f51c9fbb8c14a8f.jpg" height="50" width="50"/&gt;</cell>
                        </row><row id="fc168b8141cbf0e533c793fd621c83c8">
                            <cell style ="vertical-align:middle;text-align: center;"></cell>
                            <cell style ="vertical-align:middle;text-align: left;">
                            &lt;img src="http://www.parentfinder.com/m/photos/get_image/file/fc168b8141cbf0e533c793fd621c83c8.jpg" height="50" width="50"/&gt;</cell>
                        </row><row id="0c230ac5f3b4246e98815e756a029130">
                            <cell style ="vertical-align:middle;text-align: center;"></cell>
                            <cell style ="vertical-align:middle;text-align: left;">
                            &lt;img src="http://www.parentfinder.com/m/photos/get_image/file/0c230ac5f3b4246e98815e756a029130.jpg" height="50" width="50"/&gt;</cell>
                        </row><row id="58408f212ae22ab440ccf4ae4aef08c3">
                            <cell style ="vertical-align:middle;text-align: center;"></cell>
                            <cell style ="vertical-align:middle;text-align: left;">
                            &lt;img src="http://www.parentfinder.com/m/photos/get_image/file/58408f212ae22ab440ccf4ae4aef08c3.jpg" height="50" width="50"/&gt;</cell>
                        </row><row id="f847bb526181d99cb0bea41b7cfac5e4">
                            <cell style ="vertical-align:middle;text-align: center;"></cell>
                            <cell style ="vertical-align:middle;text-align: left;">
                            &lt;img src="http://www.parentfinder.com/m/photos/get_image/file/f847bb526181d99cb0bea41b7cfac5e4.jpg" height="50" width="50"/&gt;</cell>
                        </row><row id="70cfc90280062bb930f1ad6a74aa14b7">
                            <cell style ="vertical-align:middle;text-align: center;"></cell>
                            <cell style ="vertical-align:middle;text-align: left;">
                            &lt;img src="http://www.parentfinder.com/m/photos/get_image/file/70cfc90280062bb930f1ad6a74aa14b7.jpg" height="50" width="50"/&gt;</cell>
                        </row><row id="a2af1960c3d3b4d0658ba433aa821380">
                            <cell style ="vertical-align:middle;text-align: center;"></cell>
                            <cell style ="vertical-align:middle;text-align: left;">
                            &lt;img src="http://www.parentfinder.com/m/photos/get_image/file/a2af1960c3d3b4d0658ba433aa821380.jpg" height="50" width="50"/&gt;</cell>
                        </row><row id="e0dbabd9ab4cc439ccbf81fd1e2a2356">
                            <cell style ="vertical-align:middle;text-align: center;"></cell>
                            <cell style ="vertical-align:middle;text-align: left;">
                            &lt;img src="http://www.parentfinder.com/m/photos/get_image/file/e0dbabd9ab4cc439ccbf81fd1e2a2356.jpg" height="50" width="50"/&gt;</cell>
                        </row><row id="7ff57ed6616a584c0892459607d2350b">
                            <cell style ="vertical-align:middle;text-align: center;"></cell>
                            <cell style ="vertical-align:middle;text-align: left;">
                            &lt;img src="http://www.parentfinder.com/m/photos/get_image/file/7ff57ed6616a584c0892459607d2350b.jpg" height="50" width="50"/&gt;</cell>
                        </row><row id="52d4a9bbf153ca8d2c5a0b283fae5ee0">
                            <cell style ="vertical-align:middle;text-align: center;"></cell>
                            <cell style ="vertical-align:middle;text-align: left;">
                            &lt;img src="http://www.parentfinder.com/m/photos/get_image/file/52d4a9bbf153ca8d2c5a0b283fae5ee0.jpg" height="50" width="50"/&gt;</cell>
                        </row><row id="b12b1c8a04b7ac463a0311ade0604a2d">
                            <cell style ="vertical-align:middle;text-align: center;"></cell>
                            <cell style ="vertical-align:middle;text-align: left;">
                            &lt;img src="http://www.parentfinder.com/m/photos/get_image/file/b12b1c8a04b7ac463a0311ade0604a2d.jpg" height="50" width="50"/&gt;</cell>
                        </row><row id="729a37f27598a9706e0d7face7775e51">
                            <cell style ="vertical-align:middle;text-align: center;"></cell>
                            <cell style ="vertical-align:middle;text-align: left;">
                            &lt;img src="http://www.parentfinder.com/m/photos/get_image/file/729a37f27598a9706e0d7face7775e51.jpg" height="50" width="50"/&gt;</cell>
                        </row><row id="d9d7b1f7e2d4572ce4e3e5ed54ff623d">
                            <cell style ="vertical-align:middle;text-align: center;"></cell>
                            <cell style ="vertical-align:middle;text-align: left;">
                            &lt;img src="http://www.parentfinder.com/m/photos/get_image/file/d9d7b1f7e2d4572ce4e3e5ed54ff623d.jpg" height="50" width="50"/&gt;</cell>
                        </row><row id="777a780d0a4d99ea130fe508be47a7bf">
                            <cell style ="vertical-align:middle;text-align: center;"></cell>
                            <cell style ="vertical-align:middle;text-align: left;">
                            &lt;img src="http://www.parentfinder.com/m/photos/get_image/file/777a780d0a4d99ea130fe508be47a7bf.jpg" height="50" width="50"/&gt;</cell>
                        </row><row id="29ece64d10cdc08a6587bae21c232c3c">
                            <cell style ="vertical-align:middle;text-align: center;"></cell>
                            <cell style ="vertical-align:middle;text-align: left;">
                            &lt;img src="http://www.parentfinder.com/m/photos/get_image/file/29ece64d10cdc08a6587bae21c232c3c.jpg" height="50" width="50"/&gt;</cell>
                        </row><row id="38e45bbe294b1f8849297fd8ea846983">
                            <cell style ="vertical-align:middle;text-align: center;"></cell>
                            <cell style ="vertical-align:middle;text-align: left;">
                            &lt;img src="http://www.parentfinder.com/m/photos/get_image/file/38e45bbe294b1f8849297fd8ea846983.jpg" height="50" width="50"/&gt;</cell>
                        </row><row id="e0e1a552c977b539b6d4d06e27e86338">
                            <cell style ="vertical-align:middle;text-align: center;"></cell>
                            <cell style ="vertical-align:middle;text-align: left;">
                            &lt;img src="http://www.parentfinder.com/m/photos/get_image/file/e0e1a552c977b539b6d4d06e27e86338.jpg" height="50" width="50"/&gt;</cell>
                        </row><row id="2557ed6f2add5c930f795f374d7c44a4">
                            <cell style ="vertical-align:middle;text-align: center;"></cell>
                            <cell style ="vertical-align:middle;text-align: left;">
                            &lt;img src="http://www.parentfinder.com/m/photos/get_image/file/2557ed6f2add5c930f795f374d7c44a4.jpg" height="50" width="50"/&gt;</cell>
                        </row><row id="2a89b366025b22a44cde7b286718293c">
                            <cell style ="vertical-align:middle;text-align: center;"></cell>
                            <cell style ="vertical-align:middle;text-align: left;">
                            &lt;img src="http://www.parentfinder.com/m/photos/get_image/file/2a89b366025b22a44cde7b286718293c.jpg" height="50" width="50"/&gt;</cell>
                        </row><row id="a952cef230012318a1aa92b40dedd85b">
                            <cell style ="vertical-align:middle;text-align: center;"></cell>
                            <cell style ="vertical-align:middle;text-align: left;">
                            &lt;img src="http://www.parentfinder.com/m/photos/get_image/file/a952cef230012318a1aa92b40dedd85b.jpg" height="50" width="50"/&gt;</cell>
                        </row><row id="8e921454139a15ea6910b01c12127a31">
                            <cell style ="vertical-align:middle;text-align: center;"></cell>
                            <cell style ="vertical-align:middle;text-align: left;">
                            &lt;img src="http://www.parentfinder.com/m/photos/get_image/file/8e921454139a15ea6910b01c12127a31.jpg" height="50" width="50"/&gt;</cell>
                        </row><row id="b13ecad80511ae66961d5489064bcb07">
                            <cell style ="vertical-align:middle;text-align: center;"></cell>
                            <cell style ="vertical-align:middle;text-align: left;">
                            &lt;img src="http://www.parentfinder.com/m/photos/get_image/file/b13ecad80511ae66961d5489064bcb07.jpg" height="50" width="50"/&gt;</cell>
                        </row><row id="8228bd2bfd12359f9d9939696874f20f">
                            <cell style ="vertical-align:middle;text-align: center;"></cell>
                            <cell style ="vertical-align:middle;text-align: left;">
                            &lt;img src="http://www.parentfinder.com/m/photos/get_image/file/8228bd2bfd12359f9d9939696874f20f.jpg" height="50" width="50"/&gt;</cell>
                        </row><row id="4106482d163a6115058c8449a25f3b63">
                            <cell style ="vertical-align:middle;text-align: center;"></cell>
                            <cell style ="vertical-align:middle;text-align: left;">
                            &lt;img src="http://www.parentfinder.com/m/photos/get_image/file/4106482d163a6115058c8449a25f3b63.jpg" height="50" width="50"/&gt;</cell>
                        </row><row id="8f8d01cbbae90ab6bb400c1106719fc1">
                            <cell style ="vertical-align:middle;text-align: center;"></cell>
                            <cell style ="vertical-align:middle;text-align: left;">
                            &lt;img src="http://www.parentfinder.com/m/photos/get_image/file/8f8d01cbbae90ab6bb400c1106719fc1.jpg" height="50" width="50"/&gt;</cell>
                        </row><row id="5a369fef18052384067da13406febe7e">
                            <cell style ="vertical-align:middle;text-align: center;"></cell>
                            <cell style ="vertical-align:middle;text-align: left;">
                            &lt;img src="http://www.parentfinder.com/m/photos/get_image/file/5a369fef18052384067da13406febe7e.jpg" height="50" width="50"/&gt;</cell>
                        </row><row id="1f344f0b2e286b3db039b96f10b8a53d">
                            <cell style ="vertical-align:middle;text-align: center;"></cell>
                            <cell style ="vertical-align:middle;text-align: left;">
                            &lt;img src="http://www.parentfinder.com/m/photos/get_image/file/1f344f0b2e286b3db039b96f10b8a53d.jpg" height="50" width="50"/&gt;</cell>
                        </row><row id="0daa4c89f853ffb7ab4db86bb5ff292a">
                            <cell style ="vertical-align:middle;text-align: center;"></cell>
                            <cell style ="vertical-align:middle;text-align: left;">
                            &lt;img src="http://www.parentfinder.com/m/photos/get_image/file/0daa4c89f853ffb7ab4db86bb5ff292a.jpg" height="50" width="50"/&gt;</cell>
                        </row><row id="3718c5402e88929db9b18082f1bae583">
                            <cell style ="vertical-align:middle;text-align: center;"></cell>
                            <cell style ="vertical-align:middle;text-align: left;">
                            &lt;img src="http://www.parentfinder.com/m/photos/get_image/file/3718c5402e88929db9b18082f1bae583.jpg" height="50" width="50"/&gt;</cell>
                        </row><row id="3d3d816df56970f304b1211cef9e2ab9">
                            <cell style ="vertical-align:middle;text-align: center;"></cell>
                            <cell style ="vertical-align:middle;text-align: left;">
                            &lt;img src="http://www.parentfinder.com/m/photos/get_image/file/3d3d816df56970f304b1211cef9e2ab9.jpg" height="50" width="50"/&gt;</cell>
                        </row><row id="182a9b162eb96cd183fb3620063d4639">
                            <cell style ="vertical-align:middle;text-align: center;"></cell>
                            <cell style ="vertical-align:middle;text-align: left;">
                            &lt;img src="http://www.parentfinder.com/m/photos/get_image/file/182a9b162eb96cd183fb3620063d4639.jpg" height="50" width="50"/&gt;</cell>
                        </row><row id="0c415901c15ece559e6e6bbf419e26bb">
                            <cell style ="vertical-align:middle;text-align: center;"></cell>
                            <cell style ="vertical-align:middle;text-align: left;">
                            &lt;img src="http://www.parentfinder.com/m/photos/get_image/file/0c415901c15ece559e6e6bbf419e26bb.jpg" height="50" width="50"/&gt;</cell>
                        </row><row id="0d587e4d2d2b2824d77966f6eccb8cc6">
                            <cell style ="vertical-align:middle;text-align: center;"></cell>
                            <cell style ="vertical-align:middle;text-align: left;">
                            &lt;img src="http://www.parentfinder.com/m/photos/get_image/file/0d587e4d2d2b2824d77966f6eccb8cc6.jpg" height="50" width="50"/&gt;</cell>
                        </row><row id="844bffc7a5cfaabfe5abcb599db8800e">
                            <cell style ="vertical-align:middle;text-align: center;"></cell>
                            <cell style ="vertical-align:middle;text-align: left;">
                            &lt;img src="http://www.parentfinder.com/m/photos/get_image/file/844bffc7a5cfaabfe5abcb599db8800e.jpg" height="50" width="50"/&gt;</cell>
                        </row><row id="0f96452a7bb15f6871482828f9d6a3fa">
                            <cell style ="vertical-align:middle;text-align: center;"></cell>
                            <cell style ="vertical-align:middle;text-align: left;">
                            &lt;img src="http://www.parentfinder.com/m/photos/get_image/file/0f96452a7bb15f6871482828f9d6a3fa.jpg" height="50" width="50"/&gt;</cell>
                        </row><row id="a373e1f0226944e6de677065314c6505">
                            <cell style ="vertical-align:middle;text-align: center;"></cell>
                            <cell style ="vertical-align:middle;text-align: left;">
                            &lt;img src="http://www.parentfinder.com/m/photos/get_image/file/a373e1f0226944e6de677065314c6505.jpg" height="50" width="50"/&gt;</cell>
                        </row><row id="bda309cb530eb6b9f2046268c4064f50">
                            <cell style ="vertical-align:middle;text-align: center;"></cell>
                            <cell style ="vertical-align:middle;text-align: left;">
                            &lt;img src="http://www.parentfinder.com/m/photos/get_image/file/bda309cb530eb6b9f2046268c4064f50.jpg" height="50" width="50"/&gt;</cell>
                        </row><row id="522abaf9692e0781a7832fbc6930d903">
                            <cell style ="vertical-align:middle;text-align: center;"></cell>
                            <cell style ="vertical-align:middle;text-align: left;">
                            &lt;img src="http://www.parentfinder.com/m/photos/get_image/file/522abaf9692e0781a7832fbc6930d903.jpg" height="50" width="50"/&gt;</cell>
                        </row><row id="04aa58faf7a7bbdb1bb6864c77870b1f">
                            <cell style ="vertical-align:middle;text-align: center;"></cell>
                            <cell style ="vertical-align:middle;text-align: left;">
                            &lt;img src="http://www.parentfinder.com/m/photos/get_image/file/04aa58faf7a7bbdb1bb6864c77870b1f.jpg" height="50" width="50"/&gt;</cell>
                        </row><row id="f2978273156645ee991665d48ae0cd9c">
                            <cell style ="vertical-align:middle;text-align: center;"></cell>
                            <cell style ="vertical-align:middle;text-align: left;">
                            &lt;img src="http://www.parentfinder.com/m/photos/get_image/file/f2978273156645ee991665d48ae0cd9c.jpg" height="50" width="50"/&gt;</cell>
                        </row><row id="949a53236f548422ca9c426765907e43">
                            <cell style ="vertical-align:middle;text-align: center;"></cell>
                            <cell style ="vertical-align:middle;text-align: left;">
                            &lt;img src="http://www.parentfinder.com/m/photos/get_image/file/949a53236f548422ca9c426765907e43.jpg" height="50" width="50"/&gt;</cell>
                        </row><row id="9038724ee83522a4ffc94f4c6ba78cfe">
                            <cell style ="vertical-align:middle;text-align: center;"></cell>
                            <cell style ="vertical-align:middle;text-align: left;">
                            &lt;img src="http://www.parentfinder.com/m/photos/get_image/file/9038724ee83522a4ffc94f4c6ba78cfe.jpg" height="50" width="50"/&gt;</cell>
                        </row><row id="380e85fbf21c5872f317c8411c36b182">
                            <cell style ="vertical-align:middle;text-align: center;"></cell>
                            <cell style ="vertical-align:middle;text-align: left;">
                            &lt;img src="http://www.parentfinder.com/m/photos/get_image/file/380e85fbf21c5872f317c8411c36b182.jpg" height="50" width="50"/&gt;</cell>
                        </row><row id="c37b9d128b07d06067bdb6c5881f75c3">
                            <cell style ="vertical-align:middle;text-align: center;"></cell>
                            <cell style ="vertical-align:middle;text-align: left;">
                            &lt;img src="http://www.parentfinder.com/m/photos/get_image/file/c37b9d128b07d06067bdb6c5881f75c3.jpg" height="50" width="50"/&gt;</cell>
                        </row><row id="d050b3d6ac751a3fb37e6ddc99f5c9f5">
                            <cell style ="vertical-align:middle;text-align: center;"></cell>
                            <cell style ="vertical-align:middle;text-align: left;">
                            &lt;img src="http://www.parentfinder.com/m/photos/get_image/file/d050b3d6ac751a3fb37e6ddc99f5c9f5.jpg" height="50" width="50"/&gt;</cell>
                        </row><row id="522e6c2aabafb983e591ec3201ccafc9">
                            <cell style ="vertical-align:middle;text-align: center;"></cell>
                            <cell style ="vertical-align:middle;text-align: left;">
                            &lt;img src="http://www.parentfinder.com/m/photos/get_image/file/522e6c2aabafb983e591ec3201ccafc9.jpg" height="50" width="50"/&gt;</cell>
                        </row><row id="1795b20fe27c3129e6d9d5c469bb8b10">
                            <cell style ="vertical-align:middle;text-align: center;"></cell>
                            <cell style ="vertical-align:middle;text-align: left;">
                            &lt;img src="http://www.parentfinder.com/m/photos/get_image/file/1795b20fe27c3129e6d9d5c469bb8b10.jpg" height="50" width="50"/&gt;</cell>
                        </row><row id="4646be4d35481b1652dba45eda6c54c6">
                            <cell style ="vertical-align:middle;text-align: center;"></cell>
                            <cell style ="vertical-align:middle;text-align: left;">
                            &lt;img src="http://www.parentfinder.com/m/photos/get_image/file/4646be4d35481b1652dba45eda6c54c6.jpg" height="50" width="50"/&gt;</cell>
                        </row><row id="fa71e0e531ec0ebc209909d71c47e60a">
                            <cell style ="vertical-align:middle;text-align: center;"></cell>
                            <cell style ="vertical-align:middle;text-align: left;">
                            &lt;img src="http://www.parentfinder.com/m/photos/get_image/file/fa71e0e531ec0ebc209909d71c47e60a.jpg" height="50" width="50"/&gt;</cell>
                        </row><row id="3d596870d33ad5e432019c87f739e325">
                            <cell style ="vertical-align:middle;text-align: center;"></cell>
                            <cell style ="vertical-align:middle;text-align: left;">
                            &lt;img src="http://www.parentfinder.com/m/photos/get_image/file/3d596870d33ad5e432019c87f739e325.jpg" height="50" width="50"/&gt;</cell>
                        </row><row id="5eee9762f432428fe2743580afdd1a2f">
                            <cell style ="vertical-align:middle;text-align: center;"></cell>
                            <cell style ="vertical-align:middle;text-align: left;">
                            &lt;img src="http://www.parentfinder.com/m/photos/get_image/file/5eee9762f432428fe2743580afdd1a2f.jpg" height="50" width="50"/&gt;</cell>
                        </row><row id="3995b7a0cb5eae1991449e2cd649e688">
                            <cell style ="vertical-align:middle;text-align: center;"></cell>
                            <cell style ="vertical-align:middle;text-align: left;">
                            &lt;img src="http://www.parentfinder.com/m/photos/get_image/file/3995b7a0cb5eae1991449e2cd649e688.jpg" height="50" width="50"/&gt;</cell>
                        </row><row id="ea7d1cbea4cba047e8542a6bbe4dfb98">
                            <cell style ="vertical-align:middle;text-align: center;"></cell>
                            <cell style ="vertical-align:middle;text-align: left;">
                            &lt;img src="http://www.parentfinder.com/m/photos/get_image/file/ea7d1cbea4cba047e8542a6bbe4dfb98.jpg" height="50" width="50"/&gt;</cell>
                        </row><row id="ef8962b6011007d6dbb87d45cb2c8649">
                            <cell style ="vertical-align:middle;text-align: center;"></cell>
                            <cell style ="vertical-align:middle;text-align: left;">
                            &lt;img src="http://www.parentfinder.com/m/photos/get_image/file/ef8962b6011007d6dbb87d45cb2c8649.jpg" height="50" width="50"/&gt;</cell>
                        </row><row id="d43c0d721dc0748f0959814154c97756">
                            <cell style ="vertical-align:middle;text-align: center;"></cell>
                            <cell style ="vertical-align:middle;text-align: left;">
                            &lt;img src="http://www.parentfinder.com/m/photos/get_image/file/d43c0d721dc0748f0959814154c97756.jpg" height="50" width="50"/&gt;</cell>
                        </row><row id="3caf0a5170bde113916daca8a4ff4c2f">
                            <cell style ="vertical-align:middle;text-align: center;"></cell>
                            <cell style ="vertical-align:middle;text-align: left;">
                            &lt;img src="http://www.parentfinder.com/m/photos/get_image/file/3caf0a5170bde113916daca8a4ff4c2f.jpg" height="50" width="50"/&gt;</cell>
                        </row><row id="1445118547a2de4e66308ea175f98ae9">
                            <cell style ="vertical-align:middle;text-align: center;"></cell>
                            <cell style ="vertical-align:middle;text-align: left;">
                            &lt;img src="http://www.parentfinder.com/m/photos/get_image/file/1445118547a2de4e66308ea175f98ae9.jpg" height="50" width="50"/&gt;</cell>
                        </row><row id="7b2e3e9ae3c91cce9bc2ca976f151632">
                            <cell style ="vertical-align:middle;text-align: center;"></cell>
                            <cell style ="vertical-align:middle;text-align: left;">
                            &lt;img src="http://www.parentfinder.com/m/photos/get_image/file/7b2e3e9ae3c91cce9bc2ca976f151632.jpg" height="50" width="50"/&gt;</cell>
                        </row><row id="5b8b4a2c0e3cd5f162e9b52d76f3eca1">
                            <cell style ="vertical-align:middle;text-align: center;"></cell>
                            <cell style ="vertical-align:middle;text-align: left;">
                            &lt;img src="http://www.parentfinder.com/m/photos/get_image/file/5b8b4a2c0e3cd5f162e9b52d76f3eca1.jpg" height="50" width="50"/&gt;</cell>
                        </row><row id="76dc0438563c89355ab5d08c6ead8195">
                            <cell style ="vertical-align:middle;text-align: center;"></cell>
                            <cell style ="vertical-align:middle;text-align: left;">
                            &lt;img src="http://www.parentfinder.com/m/photos/get_image/file/76dc0438563c89355ab5d08c6ead8195.jpg" height="50" width="50"/&gt;</cell>
                        </row><row id="a9af824b557650ad22e159a3bac89635">
                            <cell style ="vertical-align:middle;text-align: center;"></cell>
                            <cell style ="vertical-align:middle;text-align: left;">
                            &lt;img src="http://www.parentfinder.com/m/photos/get_image/file/a9af824b557650ad22e159a3bac89635.jpg" height="50" width="50"/&gt;</cell>
                        </row><row id="a319b7cb5e23533c13b9a8d58022db27">
                            <cell style ="vertical-align:middle;text-align: center;"></cell>
                            <cell style ="vertical-align:middle;text-align: left;">
                            &lt;img src="http://www.parentfinder.com/m/photos/get_image/file/a319b7cb5e23533c13b9a8d58022db27.jpg" height="50" width="50"/&gt;</cell>
                        </row><row id="70f32c30589f8d5dd2d2f8031f832fb0">
                            <cell style ="vertical-align:middle;text-align: center;"></cell>
                            <cell style ="vertical-align:middle;text-align: left;">
                            &lt;img src="http://www.parentfinder.com/m/photos/get_image/file/70f32c30589f8d5dd2d2f8031f832fb0.jpg" height="50" width="50"/&gt;</cell>
                        </row><row id="94b85993ce0219565deab14600fa1bcd">
                            <cell style ="vertical-align:middle;text-align: center;"></cell>
                            <cell style ="vertical-align:middle;text-align: left;">
                            &lt;img src="http://www.parentfinder.com/m/photos/get_image/file/94b85993ce0219565deab14600fa1bcd.jpg" height="50" width="50"/&gt;</cell>
                        </row><row id="8488d9236b6927b6d19ff6e2a5860335">
                            <cell style ="vertical-align:middle;text-align: center;"></cell>
                            <cell style ="vertical-align:middle;text-align: left;">
                            &lt;img src="http://www.parentfinder.com/m/photos/get_image/file/8488d9236b6927b6d19ff6e2a5860335.jpg" height="50" width="50"/&gt;</cell>
                        </row></rows></xml>